Workbook

Sheet FLUXO
A1: MARCA | B1: CNPJ/CPF | C1: Nome | D1: EMAIL ENV | E1: CONTATO TEL REAL DEV | F1: CONTATO TEL REC DEV | G1: WHATSAPP MENS REC | H1: WHATSAPP MENS ENV | I1: CORRES DEVEDOR | J1: PROPOSTA | K1: CRVA - SOL | L1: RI SOL | M1: CRVA – POS | N1: RI POS | O1: BUSCA PROCESSUAL NEG | P1: BUSCA PROCESSUAL POS | Q1: 851 SCPC INCLUSAO | R1: CARTA ENVIADA | S1: CARTA DEVOLVIDA | T1: LIGAÇÃO ATIVA
A2: PREPARA | B2: 18.288.085/0001-10 | C2: A & D TREINAMENTOS E CURSOS LTDA - ME | D2: =IF((COUNTIFS(#REF!,$C2,#REF!,"*163*"))>=1,"SIM","") -> #REF! | E2: =IF((COUNTIFS(#REF!,$C2,#REF!,E$1))>=1,"SIM","") -> #REF! | F2: =IF((COUNTIFS(#REF!,$C2,#REF!,F$1))>=1,"SIM","") -> #REF! | G2: =IF((COUNTIFS(#REF!,$C2,#REF!,"*606*"))>=1,"SIM","") -> #REF! | H2: =IF((COUNTIFS(#REF!,$C2,#REF!,"*605*"))>=1,"SIM","") -> #REF! | I2: =IF((COUNTIFS(#REF!,$C2,#REF!,I$1))>=1,"SIM","") -> #REF! | J2: =IF((COUNTIFS(#REF!,$C2,#REF!,J$1))>=1,"SIM","") -> #REF! | K2: =IF((COUNTIFS(#REF!,$C2,#REF!,K$1))>=1,"SIM","") -> #REF! | L2: =IF((COUNTIFS(#REF!,$C2,#REF!,L$1))>=1,"SIM","") -> #REF! | M2: =IF((COUNTIFS(#REF!,$C2,#REF!,M$1))>=1,"SIM","") -> #REF! | N2: =IF((COUNTIFS(#REF!,$C2,#REF!,N$1))>=1,"SIM","") -> #REF! | P2: =IF((COUNTIFS(#REF!,$C2,#REF!,P$1))>=1,"SIM","") -> #REF! | Q2: =IF((COUNTIFS(#REF!,$C2,#REF!,Q$1))>=1,"SIM","") -> #REF! | R2: =IF((COUNTIFS(#REF!,$C2,#REF!,"*CARTA*"))>=1,"SIM","") -> #REF! | S2: =IF((COUNTIFS(#REF!,$C2,#REF!,"*CARTA NOTIFICAÇÃO/DEVOL*"))>=1,"SIM","") -> #REF! | T2: =IF((COUNTIFS(#REF!,$C2,#REF!,"*LIGAÇÃO ATIVA DEV PRIN/LOC*"))>=1,"SIM","") -> #REF!
A3: PREPARA | B3: 18.711.086/0001-26 | C3: A E S COMERCIO DE LIVROS LTDA-ME | D3: =IF((COUNTIFS(#REF!,$C3,#REF!,"*163*"))>=1,"SIM","") -> #REF! | E3: =IF((COUNTIFS(#REF!,$C3,#REF!,E$1))>=1,"SIM","") -> #REF! | F3: =IF((COUNTIFS(#REF!,$C3,#REF!,F$1))>=1,"SIM","") -> #REF! | G3: =IF((COUNTIFS(#REF!,$C3,#REF!,"*606*"))>=1,"SIM","") -> #REF! | H3: =IF((COUNTIFS(#REF!,$C3,#REF!,"*605*"))>=1,"SIM","") -> #REF! | I3: =IF((COUNTIFS(#REF!,$C3,#REF!,I$1))>=1,"SIM","") -> #REF! | J3: =IF((COUNTIFS(#REF!,$C3,#REF!,J$1))>=1,"SIM","") -> #REF! | K3: =IF((COUNTIFS(#REF!,$C3,#REF!,K$1))>=1,"SIM","") -> #REF! | L3: =IF((COUNTIFS(#REF!,$C3,#REF!,L$1))>=1,"SIM","") -> #REF! | M3: =IF((COUNTIFS(#REF!,$C3,#REF!,M$1))>=1,"SIM","") -> #REF! | N3: =IF((COUNTIFS(#REF!,$C3,#REF!,N$1))>=1,"SIM","") -> #REF! | P3: =IF((COUNTIFS(#REF!,$C3,#REF!,P$1))>=1,"SIM","") -> #REF! | Q3: =IF((COUNTIFS(#REF!,$C3,#REF!,Q$1))>=1,"SIM","") -> #REF! | R3: =IF((COUNTIFS(#REF!,$C3,#REF!,"*CARTA*"))>=1,"SIM","") -> #REF! | S3: =IF((COUNTIFS(#REF!,$C3,#REF!,"*CARTA NOTIFICAÇÃO/DEVOL*"))>=1,"SIM","") -> #REF! | T3: =IF((COUNTIFS(#REF!,$C3,#REF!,"*LIGAÇÃO ATIVA DEV PRIN/LOC*"))>=1,"SIM","") -> #REF!
A4: PREPARA | B4: 26.132.015/0001-05 | C4: A F D DA SILVA CURSOS ME | D4: =IF((COUNTIFS(#REF!,$C4,#REF!,"*163*"))>=1,"SIM","") -> #REF! | E4: =IF((COUNTIFS(#REF!,$C4,#REF!,E$1))>=1,"SIM","") -> #REF! | F4: =IF((COUNTIFS(#REF!,$C4,#REF!,F$1))>=1,"SIM","") -> #REF! | G4: =IF((COUNTIFS(#REF!,$C4,#REF!,"*606*"))>=1,"SIM","") -> #REF! | H4: =IF((COUNTIFS(#REF!,$C4,#REF!,"*605*"))>=1,"SIM","") -> #REF! | I4: =IF((COUNTIFS(#REF!,$C4,#REF!,I$1))>=1,"SIM","") -> #REF! | J4: =IF((COUNTIFS(#REF!,$C4,#REF!,J$1))>=1,"SIM","") -> #REF! | K4: =IF((COUNTIFS(#REF!,$C4,#REF!,K$1))>=1,"SIM","") -> #REF! | L4: =IF((COUNTIFS(#REF!,$C4,#REF!,L$1))>=1,"SIM","") -> #REF! | M4: =IF((COUNTIFS(#REF!,$C4,#REF!,M$1))>=1,"SIM","") -> #REF! | N4: =IF((COUNTIFS(#REF!,$C4,#REF!,N$1))>=1,"SIM","") -> #REF! | P4: =IF((COUNTIFS(#REF!,$C4,#REF!,P$1))>=1,"SIM","") -> #REF! | Q4: =IF((COUNTIFS(#REF!,$C4,#REF!,Q$1))>=1,"SIM","") -> #REF! | R4: =IF((COUNTIFS(#REF!,$C4,#REF!,"*CARTA*"))>=1,"SIM","") -> #REF! | S4: =IF((COUNTIFS(#REF!,$C4,#REF!,"*CARTA NOTIFICAÇÃO/DEVOL*"))>=1,"SIM","") -> #REF! | T4: =IF((COUNTIFS(#REF!,$C4,#REF!,"*LIGAÇÃO ATIVA DEV PRIN/LOC*"))>=1,"SIM","") -> #REF!
A5: PREPARA | B5: 26.132.015/0002-88 | C5: A F DA SILVA CURSOS ME | D5: =IF((COUNTIFS(#REF!,$C5,#REF!,"*163*"))>=1,"SIM","") -> #REF! | E5: =IF((COUNTIFS(#REF!,$C5,#REF!,E$1))>=1,"SIM","") -> #REF! | F5: =IF((COUNTIFS(#REF!,$C5,#REF!,F$1))>=1,"SIM","") -> #REF! | G5: =IF((COUNTIFS(#REF!,$C5,#REF!,"*606*"))>=1,"SIM","") -> #REF! | H5: =IF((COUNTIFS(#REF!,$C5,#REF!,"*605*"))>=1,"SIM","") -> #REF! | I5: =IF((COUNTIFS(#REF!,$C5,#REF!,I$1))>=1,"SIM","") -> #REF! | J5: =IF((COUNTIFS(#REF!,$C5,#REF!,J$1))>=1,"SIM","") -> #REF! | K5: =IF((COUNTIFS(#REF!,$C5,#REF!,K$1))>=1,"SIM","") -> #REF! | L5: =IF((COUNTIFS(#REF!,$C5,#REF!,L$1))>=1,"SIM","") -> #REF! | M5: =IF((COUNTIFS(#REF!,$C5,#REF!,M$1))>=1,"SIM","") -> #REF! | N5: =IF((COUNTIFS(#REF!,$C5,#REF!,N$1))>=1,"SIM","") -> #REF! | P5: =IF((COUNTIFS(#REF!,$C5,#REF!,P$1))>=1,"SIM","") -> #REF! | Q5: =IF((COUNTIFS(#REF!,$C5,#REF!,Q$1))>=1,"SIM","") -> #REF! | R5: =IF((COUNTIFS(#REF!,$C5,#REF!,"*CARTA*"))>=1,"SIM","") -> #REF! | S5: =IF((COUNTIFS(#REF!,$C5,#REF!,"*CARTA NOTIFICAÇÃO/DEVOL*"))>=1,"SIM","") -> #REF! | T5: =IF((COUNTIFS(#REF!,$C5,#REF!,"*LIGAÇÃO ATIVA DEV PRIN/LOC*"))>=1,"SIM","") -> #REF!
A6: PREPARA | B6: 40.501.902/0001-26 | C6: A LUZ CURSOS E TREINAMENTOS LTDA | D6: =IF((COUNTIFS(#REF!,$C6,#REF!,"*163*"))>=1,"SIM","") -> #REF! | E6: =IF((COUNTIFS(#REF!,$C6,#REF!,E$1))>=1,"SIM","") -> #REF! | F6: =IF((COUNTIFS(#REF!,$C6,#REF!,F$1))>=1,"SIM","") -> #REF! | G6: =IF((COUNTIFS(#REF!,$C6,#REF!,"*606*"))>=1,"SIM","") -> #REF! | H6: =IF((COUNTIFS(#REF!,$C6,#REF!,"*605*"))>=1,"SIM","") -> #REF! | I6: =IF((COUNTIFS(#REF!,$C6,#REF!,I$1))>=1,"SIM","") -> #REF! | J6: =IF((COUNTIFS(#REF!,$C6,#REF!,J$1))>=1,"SIM","") -> #REF! | K6: =IF((COUNTIFS(#REF!,$C6,#REF!,K$1))>=1,"SIM","") -> #REF! | L6: =IF((COUNTIFS(#REF!,$C6,#REF!,L$1))>=1,"SIM","") -> #REF! | M6: =IF((COUNTIFS(#REF!,$C6,#REF!,M$1))>=1,"SIM","") -> #REF! | N6: =IF((COUNTIFS(#REF!,$C6,#REF!,N$1))>=1,"SIM","") -> #REF! | P6: =IF((COUNTIFS(#REF!,$C6,#REF!,P$1))>=1,"SIM","") -> #REF! | Q6: =IF((COUNTIFS(#REF!,$C6,#REF!,Q$1))>=1,"SIM","") -> #REF! | R6: =IF((COUNTIFS(#REF!,$C6,#REF!,"*CARTA*"))>=1,"SIM","") -> #REF! | S6: =IF((COUNTIFS(#REF!,$C6,#REF!,"*CARTA NOTIFICAÇÃO/DEVOL*"))>=1,"SIM","") -> #REF! | T6: =IF((COUNTIFS(#REF!,$C6,#REF!,"*LIGAÇÃO ATIVA DEV PRIN/LOC*"))>=1,"SIM","") -> #REF!
A7: PREPARA | B7: 18.685.720/0003-65 | C7: A P L DOURADO CENTRO DE TREINAMENTOS | D7: =IF((COUNTIFS(#REF!,$C7,#REF!,"*163*"))>=1,"SIM","") -> #REF! | E7: =IF((COUNTIFS(#REF!,$C7,#REF!,E$1))>=1,"SIM","") -> #REF! | F7: =IF((COUNTIFS(#REF!,$C7,#REF!,F$1))>=1,"SIM","") -> #REF! | G7: =IF((COUNTIFS(#REF!,$C7,#REF!,"*606*"))>=1,"SIM","") -> #REF! | H7: =IF((COUNTIFS(#REF!,$C7,#REF!,"*605*"))>=1,"SIM","") -> #REF! | I7: =IF((COUNTIFS(#REF!,$C7,#REF!,I$1))>=1,"SIM","") -> #REF! | J7: =IF((COUNTIFS(#REF!,$C7,#REF!,J$1))>=1,"SIM","") -> #REF! | K7: =IF((COUNTIFS(#REF!,$C7,#REF!,K$1))>=1,"SIM","") -> #REF! | L7: =IF((COUNTIFS(#REF!,$C7,#REF!,L$1))>=1,"SIM","") -> #REF! | M7: =IF((COUNTIFS(#REF!,$C7,#REF!,M$1))>=1,"SIM","") -> #REF! | N7: =IF((COUNTIFS(#REF!,$C7,#REF!,N$1))>=1,"SIM","") -> #REF! | P7: =IF((COUNTIFS(#REF!,$C7,#REF!,P$1))>=1,"SIM","") -> #REF! | Q7: =IF((COUNTIFS(#REF!,$C7,#REF!,Q$1))>=1,"SIM","") -> #REF! | R7: =IF((COUNTIFS(#REF!,$C7,#REF!,"*CARTA*"))>=1,"SIM","") -> #REF! | S7: =IF((COUNTIFS(#REF!,$C7,#REF!,"*CARTA NOTIFICAÇÃO/DEVOL*"))>=1,"SIM","") -> #REF! | T7: =IF((COUNTIFS(#REF!,$C7,#REF!,"*LIGAÇÃO ATIVA DEV PRIN/LOC*"))>=1,"SIM","") -> #REF!
A8: PREPARA | B8: 19.110.795/0001-19 | C8: A&L CURSOS E CONSULTORIA LTDA - ME | D8: =IF((COUNTIFS(#REF!,$C8,#REF!,"*163*"))>=1,"SIM","") -> #REF! | E8: =IF((COUNTIFS(#REF!,$C8,#REF!,E$1))>=1,"SIM","") -> #REF! | F8: =IF((COUNTIFS(#REF!,$C8,#REF!,F$1))>=1,"SIM","") -> #REF! | G8: =IF((COUNTIFS(#REF!,$C8,#REF!,"*606*"))>=1,"SIM","") -> #REF! | H8: =IF((COUNTIFS(#REF!,$C8,#REF!,"*605*"))>=1,"SIM","") -> #REF! | I8: =IF((COUNTIFS(#REF!,$C8,#REF!,I$1))>=1,"SIM","") -> #REF! | J8: =IF((COUNTIFS(#REF!,$C8,#REF!,J$1))>=1,"SIM","") -> #REF! | K8: =IF((COUNTIFS(#REF!,$C8,#REF!,K$1))>=1,"SIM","") -> #REF! | L8: =IF((COUNTIFS(#REF!,$C8,#REF!,L$1))>=1,"SIM","") -> #REF! | M8: =IF((COUNTIFS(#REF!,$C8,#REF!,M$1))>=1,"SIM","") -> #REF! | N8: =IF((COUNTIFS(#REF!,$C8,#REF!,N$1))>=1,"SIM","") -> #REF! | P8: =IF((COUNTIFS(#REF!,$C8,#REF!,P$1))>=1,"SIM","") -> #REF! | Q8: =IF((COUNTIFS(#REF!,$C8,#REF!,Q$1))>=1,"SIM","") -> #REF! | R8: =IF((COUNTIFS(#REF!,$C8,#REF!,"*CARTA*"))>=1,"SIM","") -> #REF! | S8: =IF((COUNTIFS(#REF!,$C8,#REF!,"*CARTA NOTIFICAÇÃO/DEVOL*"))>=1,"SIM","") -> #REF! | T8: =IF((COUNTIFS(#REF!,$C8,#REF!,"*LIGAÇÃO ATIVA DEV PRIN/LOC*"))>=1,"SIM","") -> #REF!
A9: PREPARA | B9: 13.509.635/0001-60 | C9: A. J. CURSOS PROFISSIONALIZANTES LTDA ME | D9: =IF((COUNTIFS(#REF!,$C9,#REF!,"*163*"))>=1,"SIM","") -> #REF! | E9: =IF((COUNTIFS(#REF!,$C9,#REF!,E$1))>=1,"SIM","") -> #REF! | F9: =IF((COUNTIFS(#REF!,$C9,#REF!,F$1))>=1,"SIM","") -> #REF! | G9: =IF((COUNTIFS(#REF!,$C9,#REF!,"*606*"))>=1,"SIM","") -> #REF! | H9: =IF((COUNTIFS(#REF!,$C9,#REF!,"*605*"))>=1,"SIM","") -> #REF! | I9: =IF((COUNTIFS(#REF!,$C9,#REF!,I$1))>=1,"SIM","") -> #REF! | J9: =IF((COUNTIFS(#REF!,$C9,#REF!,J$1))>=1,"SIM","") -> #REF! | K9: =IF((COUNTIFS(#REF!,$C9,#REF!,K$1))>=1,"SIM","") -> #REF! | L9: =IF((COUNTIFS(#REF!,$C9,#REF!,L$1))>=1,"SIM","") -> #REF! | M9: =IF((COUNTIFS(#REF!,$C9,#REF!,M$1))>=1,"SIM","") -> #REF! | N9: =IF((COUNTIFS(#REF!,$C9,#REF!,N$1))>=1,"SIM","") -> #REF! | P9: =IF((COUNTIFS(#REF!,$C9,#REF!,P$1))>=1,"SIM","") -> #REF! | Q9: =IF((COUNTIFS(#REF!,$C9,#REF!,Q$1))>=1,"SIM","") -> #REF! | R9: =IF((COUNTIFS(#REF!,$C9,#REF!,"*CARTA*"))>=1,"SIM","") -> #REF! | S9: =IF((COUNTIFS(#REF!,$C9,#REF!,"*CARTA NOTIFICAÇÃO/DEVOL*"))>=1,"SIM","") -> #REF! | T9: =IF((COUNTIFS(#REF!,$C9,#REF!,"*LIGAÇÃO ATIVA DEV PRIN/LOC*"))>=1,"SIM","") -> #REF!
A10: PREPARA | B10: 14.107.024/0001-59 | C10: A2E EMPRESARIAL LTDA | D10: =IF((COUNTIFS(#REF!,$C10,#REF!,"*163*"))>=1,"SIM","") -> #REF! | E10: =IF((COUNTIFS(#REF!,$C10,#REF!,E$1))>=1,"SIM","") -> #REF! | F10: =IF((COUNTIFS(#REF!,$C10,#REF!,F$1))>=1,"SIM","") -> #REF! | G10: =IF((COUNTIFS(#REF!,$C10,#REF!,"*606*"))>=1,"SIM","") -> #REF! | H10: =IF((COUNTIFS(#REF!,$C10,#REF!,"*605*"))>=1,"SIM","") -> #REF! | I10: =IF((COUNTIFS(#REF!,$C10,#REF!,I$1))>=1,"SIM","") -> #REF! | J10: =IF((COUNTIFS(#REF!,$C10,#REF!,J$1))>=1,"SIM","") -> #REF! | K10: =IF((COUNTIFS(#REF!,$C10,#REF!,K$1))>=1,"SIM","") -> #REF! | L10: =IF((COUNTIFS(#REF!,$C10,#REF!,L$1))>=1,"SIM","") -> #REF! | M10: =IF((COUNTIFS(#REF!,$C10,#REF!,M$1))>=1,"SIM","") -> #REF! | N10: =IF((COUNTIFS(#REF!,$C10,#REF!,N$1))>=1,"SIM","") -> #REF! | P10: =IF((COUNTIFS(#REF!,$C10,#REF!,P$1))>=1,"SIM","") -> #REF! | Q10: =IF((COUNTIFS(#REF!,$C10,#REF!,Q$1))>=1,"SIM","") -> #REF! | R10: =IF((COUNTIFS(#REF!,$C10,#REF!,"*CARTA*"))>=1,"SIM","") -> #REF! | S10: =IF((COUNTIFS(#REF!,$C10,#REF!,"*CARTA NOTIFICAÇÃO/DEVOL*"))>=1,"SIM","") -> #REF! | T10: =IF((COUNTIFS(#REF!,$C10,#REF!,"*LIGAÇÃO ATIVA DEV PRIN/LOC*"))>=1,"SIM","") -> #REF!
A11: MICROLINS | B11: 30.110.532/0001-42 | C11: A4B PARELHEIROS TECNOLOGIA E TREINAMENTOS LTDA | D11: =IF((COUNTIFS(#REF!,$C11,#REF!,"*163*"))>=1,"SIM","") -> #REF! | E11: =IF((COUNTIFS(#REF!,$C11,#REF!,E$1))>=1,"SIM","") -> #REF! | F11: =IF((COUNTIFS(#REF!,$C11,#REF!,F$1))>=1,"SIM","") -> #REF! | G11: =IF((COUNTIFS(#REF!,$C11,#REF!,"*606*"))>=1,"SIM","") -> #REF! | H11: =IF((COUNTIFS(#REF!,$C11,#REF!,"*605*"))>=1,"SIM","") -> #REF! | I11: =IF((COUNTIFS(#REF!,$C11,#REF!,I$1))>=1,"SIM","") -> #REF! | J11: =IF((COUNTIFS(#REF!,$C11,#REF!,J$1))>=1,"SIM","") -> #REF! | K11: =IF((COUNTIFS(#REF!,$C11,#REF!,K$1))>=1,"SIM","") -> #REF! | L11: =IF((COUNTIFS(#REF!,$C11,#REF!,L$1))>=1,"SIM","") -> #REF! | M11: =IF((COUNTIFS(#REF!,$C11,#REF!,M$1))>=1,"SIM","") -> #REF! | N11: =IF((COUNTIFS(#REF!,$C11,#REF!,N$1))>=1,"SIM","") -> #REF! | P11: =IF((COUNTIFS(#REF!,$C11,#REF!,P$1))>=1,"SIM","") -> #REF! | Q11: =IF((COUNTIFS(#REF!,$C11,#REF!,Q$1))>=1,"SIM","") -> #REF! | R11: =IF((COUNTIFS(#REF!,$C11,#REF!,"*CARTA*"))>=1,"SIM","") -> #REF! | S11: =IF((COUNTIFS(#REF!,$C11,#REF!,"*CARTA NOTIFICAÇÃO/DEVOL*"))>=1,"SIM","") -> #REF! | T11: =IF((COUNTIFS(#REF!,$C11,#REF!,"*LIGAÇÃO ATIVA DEV PRIN/LOC*"))>=1,"SIM","") -> #REF!
A12: MICROLINS | B12: 10.746.134/0001-00 | C12: A4B TECNOLOGIA E TREINAMENTO LTDA | D12: =IF((COUNTIFS(#REF!,$C12,#REF!,"*163*"))>=1,"SIM","") -> #REF! | E12: =IF((COUNTIFS(#REF!,$C12,#REF!,E$1))>=1,"SIM","") -> #REF! | F12: =IF((COUNTIFS(#REF!,$C12,#REF!,F$1))>=1,"SIM","") -> #REF! | G12: =IF((COUNTIFS(#REF!,$C12,#REF!,"*606*"))>=1,"SIM","") -> #REF! | H12: =IF((COUNTIFS(#REF!,$C12,#REF!,"*605*"))>=1,"SIM","") -> #REF! | I12: =IF((COUNTIFS(#REF!,$C12,#REF!,I$1))>=1,"SIM","") -> #REF! | J12: =IF((COUNTIFS(#REF!,$C12,#REF!,J$1))>=1,"SIM","") -> #REF! | K12: =IF((COUNTIFS(#REF!,$C12,#REF!,K$1))>=1,"SIM","") -> #REF! | L12: =IF((COUNTIFS(#REF!,$C12,#REF!,L$1))>=1,"SIM","") -> #REF! | M12: =IF((COUNTIFS(#REF!,$C12,#REF!,M$1))>=1,"SIM","") -> #REF! | N12: =IF((COUNTIFS(#REF!,$C12,#REF!,N$1))>=1,"SIM","") -> #REF! | P12: =IF((COUNTIFS(#REF!,$C12,#REF!,P$1))>=1,"SIM","") -> #REF! | Q12: =IF((COUNTIFS(#REF!,$C12,#REF!,Q$1))>=1,"SIM","") -> #REF! | R12: =IF((COUNTIFS(#REF!,$C12,#REF!,"*CARTA*"))>=1,"SIM","") -> #REF! | S12: =IF((COUNTIFS(#REF!,$C12,#REF!,"*CARTA NOTIFICAÇÃO/DEVOL*"))>=1,"SIM","") -> #REF! | T12: =IF((COUNTIFS(#REF!,$C12,#REF!,"*LIGAÇÃO ATIVA DEV PRIN/LOC*"))>=1,"SIM","") -> #REF!
A13: MICROLINS | B13: 26.801.648/0001-50 | C13: ABJ CURSOS PROFISSIONALIZANTES LTDA ME | D13: =IF((COUNTIFS(#REF!,$C13,#REF!,"*163*"))>=1,"SIM","") -> #REF! | E13: =IF((COUNTIFS(#REF!,$C13,#REF!,E$1))>=1,"SIM","") -> #REF! | F13: =IF((COUNTIFS(#REF!,$C13,#REF!,F$1))>=1,"SIM","") -> #REF! | G13: =IF((COUNTIFS(#REF!,$C13,#REF!,"*606*"))>=1,"SIM","") -> #REF! | H13: =IF((COUNTIFS(#REF!,$C13,#REF!,"*605*"))>=1,"SIM","") -> #REF! | I13: =IF((COUNTIFS(#REF!,$C13,#REF!,I$1))>=1,"SIM","") -> #REF! | J13: =IF((COUNTIFS(#REF!,$C13,#REF!,J$1))>=1,"SIM","") -> #REF! | K13: =IF((COUNTIFS(#REF!,$C13,#REF!,K$1))>=1,"SIM","") -> #REF! | L13: =IF((COUNTIFS(#REF!,$C13,#REF!,L$1))>=1,"SIM","") -> #REF! | M13: =IF((COUNTIFS(#REF!,$C13,#REF!,M$1))>=1,"SIM","") -> #REF! | N13: =IF((COUNTIFS(#REF!,$C13,#REF!,N$1))>=1,"SIM","") -> #REF! | P13: =IF((COUNTIFS(#REF!,$C13,#REF!,P$1))>=1,"SIM","") -> #REF! | Q13: =IF((COUNTIFS(#REF!,$C13,#REF!,Q$1))>=1,"SIM","") -> #REF! | R13: =IF((COUNTIFS(#REF!,$C13,#REF!,"*CARTA*"))>=1,"SIM","") -> #REF! | S13: =IF((COUNTIFS(#REF!,$C13,#REF!,"*CARTA NOTIFICAÇÃO/DEVOL*"))>=1,"SIM","") -> #REF! | T13: =IF((COUNTIFS(#REF!,$C13,#REF!,"*LIGAÇÃO ATIVA DEV PRIN/LOC*"))>=1,"SIM","") -> #REF!
... A783: PEOPLE | B783: 16.746.102/0001-90 | C783: ZESC ZL FORMACAO COMPLETA LTDA | D783: =IF((COUNTIFS(#REF!,$C783,#REF!,"*163*"))>=1,"SIM","") -> #REF! | E783: =IF((COUNTIFS(#REF!,$C783,#REF!,E$1))>=1,"SIM","") -> #REF! | F783: =IF((COUNTIFS(#REF!,$C783,#REF!,F$1))>=1,"SIM","") -> #REF! | G783: =IF((COUNTIFS(#REF!,$C783,#REF!,"*606*"))>=1,"SIM","") -> #REF! | H783: =IF((COUNTIFS(#REF!,$C783,#REF!,"*605*"))>=1,"SIM","") -> #REF! | I783: =IF((COUNTIFS(#REF!,$C783,#REF!,I$1))>=1,"SIM","") -> #REF! | J783: =IF((COUNTIFS(#REF!,$C783,#REF!,J$1))>=1,"SIM","") -> #REF! | K783: =IF((COUNTIFS(#REF!,$C783,#REF!,K$1))>=1,"SIM","") -> #REF! | L783: =IF((COUNTIFS(#REF!,$C783,#REF!,L$1))>=1,"SIM","") -> #REF! | M783: =IF((COUNTIFS(#REF!,$C783,#REF!,M$1))>=1,"SIM","") -> #REF! | N783: =IF((COUNTIFS(#REF!,$C783,#REF!,N$1))>=1,"SIM","") -> #REF! | P783: =IF((COUNTIFS(#REF!,$C783,#REF!,P$1))>=1,"SIM","") -> #REF! | Q783: =IF((COUNTIFS(#REF!,$C783,#REF!,Q$1))>=1,"SIM","") -> #REF! | R783: =IF((COUNTIFS(#REF!,$C783,#REF!,"*CARTA*"))>=1,"SIM","") -> #REF! | S783: =IF((COUNTIFS(#REF!,$C783,#REF!,"*CARTA NOTIFICAÇÃO/DEVOL*"))>=1,"SIM","") -> #REF! | T783: =IF((COUNTIFS(#REF!,$C783,#REF!,"*LIGAÇÃO ATIVA DEV PRIN/LOC*"))>=1,"SIM","") -> #REF!

Sheet AJUIZADOS
A1: MARCA | B1: CNPJ/CPF | C1: NOME | D1: VALOR SISTEMA | E1: VALOR DA CAUSA | F1: DATA INICIO DO FLUXO | G1: AGUARDA PARECER MARCA | H1: AGUARDA PARECER JURÍDICO | I1: AGUARDA PARECER FINANCEIRO | J1: PARECER DESFAVORÁVEL | K1: PARECER OK | L1: AGUARDA PROCURAÇÃO | M1: PRODUÇÃO | N1: PROTOCOLADA | O1: DATA DISTRIBUIÇÃO | P1: Nº DO PROC | Q1: OBSERVAÇÕES
A2: =VLOOKUP(C2,'BASE DE DADOS'!A:B,2,FALSE) -> PREPARA INATIVOS | B2: 18.288.085/0001-10 | C2: A & D TREINAMENTOS E CURSOS LTDA - ME | D2: 247592.84 | E2: 98657.32 | N2: SIM | O2: 44607 | P2: Proc: 1007297-93.2022.8.26.0576
A3: =VLOOKUP(C3,'BASE DE DADOS'!A:B,2,FALSE) -> ENSINA MAIS INATIVOS | B3: 28.081.837/0001-21 | C3: ACS CONSULTORIA EM EDUCACAO TREINAMENTO E CAPACITACAO EIRELI | D3: 10764.75 | E3: 23372.31 | N3: SIM | O3: 44818 | P3: Proc: 1051179-08.2022.8.26.0576 | Q3: ENVIADO EM 05/05/2022.
A4: =VLOOKUP(C4,'BASE DE DADOS'!A:B,2,FALSE) -> PREPARA INATIVOS | B4: 07.243.416/0001-80 | C4: AGF SERVICOES POSTAIS LTDA | D4: 88418.25 | E4: 22921.63 | N4: SIM | O4: 44721 | P4: Proc: 1030490-40.2022.8.26.0576
A5: =VLOOKUP(C5,'BASE DE DADOS'!A:B,2,FALSE) -> ENSINA MAIS INATIVOS | B5: 06.555.129/0001-42 | C5: ALEXANDRE MARIA PETRONILHO ME | D5: 96836.46 | E5: 117836.36 | N5: SIM | O5: 44516 | P5: Proc: 1058279-48.2021.8.26.0576
A6: PREPARA | B6: 21.687.002/0001-70 | C6: ANDERSON CAMARGO BITENCOURT - EIRELI | D6: 19916.34 | E6: 34097.47 | N6: SIM | O6: 44645 | P6: Proc: 10146638620228260576 | Q6: ACORDO FORMALIZADO -
A7: =VLOOKUP(C7,'BASE DE DADOS'!A:B,2,FALSE) -> PREPARA INATIVOS | B7: 10.403.462/0001-03 | C7: APRENDE ILHABELA CURSOS PROFISSIONALIZANTES LTDA | D7: 50921 | E7: 14750.62 | N7: SIM | O7: 44853 | P7: Proc:1058293-95.2022.8.26.0576 | Q7: ENVIADO EM 03/08/2022.
A8: =VLOOKUP(C8,'BASE DE DADOS'!A:B,2,FALSE) -> PREPARA INATIVOS | B8: 10.790.733/0001-20 | C8: ARAUJO & PARANHOS CURSOS PROFISSIONALIZANTES LTDA | D8: 26244.5 | E8: 8997.12 | N8: SIM | O8: 45084 | P8: Proc: 1028212-32.2023.8.26.0576 | Q8: ENVIADO EM 01/09/2022.
A9: =VLOOKUP(C9,'BASE DE DADOS'!A:B,2,FALSE) -> PREPARA INATIVOS | B9: 34.878.293/0001-26 | C9: ARDNAEL CURSOS PROFISSIONALIZANTES LTDA | D9: 87519.41 | E9: 79056.87 | N9: SIM | O9: 45682 | P9: Proc: 1000043-36.2025.8.26.0359 | Q9: ENVIADO EM 22/07/2022. Aguarda baixa, 05/09
A10: =VLOOKUP(C10,'BASE DE DADOS'!A:B,2,FALSE) -> MICROLINS INATIVOS | B10: 07.731.343/0001-75 | C10: B & D FORMACAO PROFISSIONAL LTDA ME | D10: 142117.2 | E10: 236518.82 | N10: SIM | O10: 44691 | P10: Proc: 1019556-51.2022.8.26.0114
A11: =VLOOKUP(C11,'BASE DE DADOS'!A:B,2,FALSE) -> PREPARA INATIVOS | B11: 14.353.416/0001-06 | C11: BOURBON CURSOS PROFISSIONALIZANTES LTDA - ME | D11: 100000 | J11: SIM | Q11: ENVIADO EM 23/03/2022. "A cobrança será ajuizada pelo outro escritório conforme diretriz da Dra. Ana em email enviado para colega Paula".
A12: =VLOOKUP(C12,'BASE DE DADOS'!A:B,2,FALSE) -> PREPARA INATIVOS | B12: 24.680.658/0001-50 | C12: C. C. PORFIRIO - ME | D12: 10468.48 | E12: 18217.98 | N12: SIM | O12: 44573 | P12: Proc: 0009737-11.2024.8.26.0576
A13: =VLOOKUP(C13,'BASE DE DADOS'!A:B,2,FALSE) -> PREPARA INATIVOS | B13: 29.182.183/0001-95 | C13: C.M. DE FREITAS MARTINEZ | D13: 166771.65 | J13: SIM | Q13: OK TÍTULOS BAIXADOS.
A14: =VLOOKUP(C14,'BASE DE DADOS'!A:B,2,FALSE) -> PREPARA INATIVOS | B14: 432.353.598-85 | C14: CAIQUE FARIA TRINDADE | D14: 20707.3 | E14: 30901.51 | N14: SIM | O14: 44657 | P14: Proc: 1017048-07.2022.8.26.0576
A15: =VLOOKUP(C15,'BASE DE DADOS'!A:B,2,FALSE) -> ENSINA MAIS INATIVOS | B15: 17.836.947/0001-30 | C15: CAMINHO BELO COMPLEMENTO ESCOLAR LTDA | D15: 14636.12 | E15: 83388.8 | N15: SIM | O15: 44494 | P15: Proc: 1054440-15.2021.8.26.0576 | R15: 83388.8 | S15: 1054440-15.2021.8.26.0576
A16: =VLOOKUP(C16,'BASE DE DADOS'!A:B,2,FALSE) -> MICROLINS INATIVOS | B16: 03.346.371/0001-18 | C16: CASE-CONSULT. ADM. SERVICOS E EVENTOS LTDA - ME | D16: 20254.85 | E16: 23704.98 | N16: SIM | O16: 44704 | P16: Proc: 1021713-94.2022.8.26.0114 | Q16: ENVIADO EM 03/02/2022, TEM TÍTULOS PRESCRITOS.
A17: =VLOOKUP(C17,'BASE DE DADOS'!A:B,2,FALSE) -> PREPARA INATIVOS | B17: 22.067.184/0001-40 | C17: CAVALCANTE & PANIAGO CURSOS PROFISSIONALIZANTES LT | D17: 31662.01 | E17: 81151.5 | N17: SIM | O17: 44573 | P17: Proc: 1000856-96.2022.8.26.0576
A18: =VLOOKUP(C18,'BASE DE DADOS'!A:B,2,FALSE) -> PREPARA INATIVOS | B18: 10.612.027/0001-99 | C18: CENTRO DE FORMACAO PROFISSIONAL DE ANAPOLIS LTDA | D18: 147520.14 | E18: 99892.9 | N18: SIM | O18: 44981 | P18: Proc: 1009273-04.2023.8.26.0576 | Q18: ENVIADO EM 31/08/2022.
A19: =VLOOKUP(C19,'BASE DE DADOS'!A:B,2,FALSE) -> PREPARA INATIVOS | B19: 10.612.027/0001-99 | C19: CENTRO DE FORMACAO PROFISSIONAL DE ANAPOLIS LTDA | D19: 89958.2 | E19: 89958.2 | N19: SIM | O19: 45180 | P19: Proc: 1045435-95.2023.8.26.0576 | Q19: Ação executiva
A20: PREPARA | B20: 317.192.678-47 | C20: CLEITON ANTONIO LANZA | D20: 20973.11 | J20: SIM
A21: =VLOOKUP(C21,'BASE DE DADOS'!A:B,2,FALSE) -> PREPARA INATIVOS | B21: 14.853.374/0001-64 | C21: CONQUISTA CURSOS PROFISSIONALIZANTES LTDA ME | D21: 75618.75 | E21: 42032.01 | N21: SIM | O21: 44649 | P21: Proc: 1015302-07.2022.8.26.0576
A22: =VLOOKUP(C22,'BASE DE DADOS'!A:B,2,FALSE) -> PREPARA INATIVOS | B22: 13.193.705/0001-14 | C22: CTM CURSOS PROFISSIONALIZANTES LTDA | D22: 120625.82 | E22: 37881.1 | N22: SIM | O22: 44721 | P22: Proc: 1030497-32.2022.8.26.0576 | Q22: AGUARDO GISLAINE SOBRE CHEQUES (OUTRA UNIDADE DO RODRIGO É A CTM)
A23: =VLOOKUP(C23,'BASE DE DADOS'!A:B,2,FALSE) -> PREPARA INATIVOS | B23: 13.193.705/0001-14 | C23: CTM CURSOS PROFISSIONALIZANTES LTDA | D23: 56301.6 | E23: 56301.6 | N23: SIM | O23: 45014 | P23: Proc: 1015680-26.2023.8.26.0576 | Q23: Ajuizada monitória em face de THATIANA RODRIGUES DA COSTA
A24: =VLOOKUP(C24,'BASE DE DADOS'!A:B,2,FALSE) -> PREPARA INATIVOS | B24: 13.567.244/0001-00 | C24: CURSOS PREPARA CAMACARI LTDA | D24: 242985.27 | E24: 28938.63 | N24: SIM | O24: 44791 | P24: Proc: 1045335-77.2022.8.26.0576 | Q24: ENVIADO EM 28/04/2022. Execução
A25: =VLOOKUP(C25,'BASE DE DADOS'!A:B,2,FALSE) -> PREPARA INATIVOS | B25: 13.567.244/0001-00 | C25: CURSOS PREPARA CAMACARI LTDA | D25: 347653.83 | E25: 347653.83 | N25: SIM | O25: 45061 | P25: Proc: 1023794-51.2023.8.26.0576 | Q25: Monitória.
A26: =VLOOKUP(C26,'BASE DE DADOS'!A:B,2,FALSE) -> PREPARA INATIVOS | B26: 30.810.174/0001-80 | C26: CURSOS PREPARA SALVADOR RIO VERMELHO LTDA | D26: 105921.83 | E26: 138189.11 | N26: SIM | O26: 45107 | P26: Proc: 1032264-71.2023.8.26.0576
A27: MICROLINS | B27: 19.510.124/0001-45 | C27: D E F CURSOS PROFISSIONALIZANTES LTDA ME | D27: 379.08 | J27: SIM | Q27: BAIXAS REALIZADAS
A28: =VLOOKUP(C28,'BASE DE DADOS'!A:B,2,FALSE) -> PREPARA INATIVOS | B28: 18.540.892/0001-89 | C28: DAMIAO E LOBO SERVICOS EDUCACIONAIS LTDA | D28: 63160.93 | E28: 70951.22 | N28: SIM | O28: 45005 | P28: Proc: 1013857-17.2023.8.26.0576 | Q28: OBS.: TEM MAIS UMA MONETÓRIAS: N° DE PROCESSO: 1069862-93.2022.8.26.0576 - Data de distribuíção: 17/01/2023 - Valor da Ação: R$ 47.997,93
A29: =VLOOKUP(C29,'BASE DE DADOS'!A:B,2,FALSE) -> PREPARA INATIVOS | B29: 110.862.857-51 | C29: DENYSE ROCHA DA SILVA | D29: 30000 | E29: 84342.17 | N29: SIM | O29: 45036 | P29: Proc: 1019746-49.2023.8.26.0576 | Q29: ENVIADO EM 24/03/2022. Aguarda cópa dos cheques (Taxa de Franquia) da Gislaine, 27/01/2023
A30: =VLOOKUP(C30,'BASE DE DADOS'!A:B,2,FALSE) -> ENSINA MAIS INATIVOS | B30: 130.897.221-00 | C30: DIVINA ARMINDA FERREIRA | D30: 67989.67 | J30: SIM
A31: =VLOOKUP(C31,'BASE DE DADOS'!A:B,2,FALSE) -> PREPARA INATIVOS | B31: 089.925.997-90 | C31: DOUGLAS SANGES LAFERE MESQUITA | D31: 11905.33 | E31: 11905.33 | N31: SIM | O31: 44844 | P31: Proc: 1056686-47.2022.8.26.0576 | Q31: ENVIADO EM 17/06/2022.(Execução)
A32: =VLOOKUP(C32,'BASE DE DADOS'!A:B,2,FALSE) -> PREPARA INATIVOS | B32: 089.925.997-90 | C32: DOUGLAS SANGES LAFERE MESQUITA | D32: 77663.75 | E32: 77663.75 | N32: SIM | O32: 44895 | P32: Proc: 1066618-59.2022.8.26.0576 | Q32: Monitória. Aguarda valor da ação.
A33: =VLOOKUP(C33,'BASE DE DADOS'!A:B,2,FALSE) -> PREPARA INATIVOS | B33: 11.592.964/0001-92 | C33: DR SILVA TREINAMENTOS E CURSOS | D33: 104731.37 | E33: 119146.27 | N33: SIM | O33: 44973 | P33: Proc: 1007672-60.2023.8.26.0576
A34: =VLOOKUP(C34,'BASE DE DADOS'!A:B,2,FALSE) -> MICROLINS | B34: 21.434.842/0002-02 | C34: EDMILSON GOMES PEREIRA | D34: 71640.23 | E34: 121945.92 | N34: SIM | O34: 45026 | P34: Proc: 1050398-14.2022.8.26.0114 | Q34: MC0354
A35: =VLOOKUP(C35,'BASE DE DADOS'!A:B,2,FALSE) -> PREPARA INATIVOS | B35: 13.969.911/0001-73 | C35: EDUCACAO PARA A VIDA CURSOS PROFISSIONALIZANTES LT | D35: 91403.57 | E35: 46632.69 | N35: SIM | O35: 44777 | P35: Proc: 0001480-94.2024.8.26.0576
A36: =VLOOKUP(C36,'BASE DE DADOS'!A:B,2,FALSE) -> ENSINA MAIS INATIVOS | B36: 11.060.716/0001-09 | C36: EDUTEC SERVICOS DE ESC. E TREI. EM DES. PROF. LTDA | D36: 35148.15 | E36: 51061.57 | N36: SIM | O36: 44524 | P36: Proc: 0001482-64.2024.8.26.0576 | S36: 1060118-11.2021.8.26.0576
A37: =VLOOKUP(C37,'BASE DE DADOS'!A:B,2,FALSE) -> PREPARA INATIVOS | B37: 10.635.994/0001-76 | C37: F J CURSOS PROFISSIONALIZANTERS LTDA - ME | D37: 20863.7 | J37: SIM | Q37: ENVIADO EM 17/08/2022. Cheque não possui carimbo de devolução. Solicitei autorização ao Marcelo para baixa 23/02/23.
A38: MICROLINS | B38: 09.674.477/0001-27 | C38: F.K.J FORMACAO PROFISSIONAL LTDA ME | D38: 21061.78 | J38: SIM | Q38: Baixa realizada - Vitória, 26/09.
A39: =VLOOKUP(C39,'BASE DE DADOS'!A:B,2,FALSE) -> PREPARA INATIVOS | B39: 15.872.566/0001-80 | C39: F.T.C DE CASTRO - ME | D39: 23436.3 | E39: 4537.88 | N39: SIM | O39: 44848 | P39: Proc: 1057353-33.2022.8.26.0576 | Q39: ENVIADO EM 12/05/2022.
A40: MICROLINS | B40: 115.821.647-54 | C40: FERNANDO JOSE LEANDRO DE SOUZA | D40: 15561.28 | J40: SIM | Q40: ENVIADO EM 18/04/2022.
A41: =VLOOKUP(C41,'BASE DE DADOS'!A:B,2,FALSE) -> ENSINA MAIS INATIVOS | B41: 22.725.948/0001-47 | C41: FTW- CURSOS PROFISSIONALIZANTES E TREINAMENTOS LTD | D41: 73614.1 | E41: 48420.44 | N41: SIM | O41: 45005 | P41: Proc: 1013853-77.2023.8.26.0576 | Q41: ENVIADO EM 12/07/2022.
A42: =VLOOKUP(C42,'BASE DE DADOS'!A:B,2,FALSE) -> MICROLINS | B42: 20.280.371/0002-62 | C42: G P CURSOS PROFISSIONALIZANTES LTDA - ME | D42: 36181.54 | E42: 56368.25 | N42: SIM | O42: 44882 | P42: Proc: 1050164-32.2022.8.26.0114 | Q42: EDMILSON GOMES PEREIRA - MC0359
A43: =VLOOKUP(C43,'BASE DE DADOS'!A:B,2,FALSE) -> MICROLINS | B43: 08.529.944/0001-62 | C43: G P INFO SERVICE LTDA - ME | D43: 29308.82 | E43: 45469.47 | N43: SIM | O43: 45180 | P43: Proc: 1039948-75.2023.8.26.0114 | Q43: EDMILSON GOMES PEREIRA - MC0190 -Comprovantes solicitados (Micheli -> Ariane) a base entregadora (comprovantes de entrega. Nf's 16535, 16906, 17697 e 18241 - 05/09). Reiterado em 05/12. Solicitada diretriz ao Marcelo, 27/04.
A44: =VLOOKUP(C44,'BASE DE DADOS'!A:B,2,FALSE) -> MICROLINS INATIVOS | B44: 08.035.142/0002-87 | C44: G P INFORMATICA E EDITORACAO LTDA | D44: 1248.53 | J44: SIM | Q44: EDMILSON GOMES PEREIRA - MC0234. Solicitada autorização para baixa, 21/11.. O devedor recebeu notificação assinada pela credora declarando como valor dos débitos em aberto "R$ 0,00" no fechamento da escola e comprovou com ata notarial e fotos o encerramento da unidade
A45: =VLOOKUP(C45,'BASE DE DADOS'!A:B,2,FALSE) -> MICROLINS INATIVOS | B45: 08.035.142/0001-04 | C45: G P INFORMATICA E EDITORACAO LTDA | D45: 3450.37 | J45: SIM | Q45: EDMILSON GOMES PEREIRA
A46: =VLOOKUP(C46,'BASE DE DADOS'!A:B,2,FALSE) -> MICROLINS INATIVOS | B46: 21.434.842/0001-21 | C46: G P QUALIFICACAO PROFISSIONAL LTDA ME | D46: 72351.14 | E46: 116.953,77 | N46: SIM | O46: 45026 | P46: Proc: 1050400-81.2022.8.26.0114 | Q46: EDMILSON GOMES PEREIRA - MC0363
A47: =VLOOKUP(C47,'BASE DE DADOS'!A:B,2,FALSE) -> ENSINA MAIS INATIVOS | B47: 316.335.728-89 | C47: GILBERTO DE BRITO JUNIOR | D47: 22172.16 | E47: 58748.17 | N47: SIM | O47: 44503 | P47: Proc: 1055988-75.2021.8.26.0576
A48: =VLOOKUP(C48,'BASE DE DADOS'!A:B,2,FALSE) -> MICROLINS INATIVOS | B48: 20.280.371/0001-81 | C48: GP CURSOS PROFISSIONALIZANTES LTDA ME | D48: 42209.28 | E48: 73508.45 | N48: SIM | O48: 44862 | P48: Proc: 1050163-47.2022.8.26.0114 | Q48: Essa unidade é do mesmo Franqueado Edmilson, que pediu encerramento de outras 9 unidades, solicitei à dra. Ana que aguardasse eu realizar o parecer das outras unidades, para dicidirmos em conjunto.
A49: =VLOOKUP(C49,'BASE DE DADOS'!A:B,2,FALSE) -> MICROLINS INATIVOS | B49: 19.727.851/0001-69 | C49: GP FROTA CURSOS PROFISSIONALIZANTES LTDA | D49: 16461.97 | E49: 26761.5 | N49: SIM | O49: 45160 | P49: Proc: 1032262-32.2023.8.26.0114 | Q49: EDMILSON GOMES PEREIRA - MC0336
A50: =VLOOKUP(C50,'BASE DE DADOS'!A:B,2,FALSE) -> PREPARA INATIVOS | B50: 17.377.252/0001-37 | C50: GRUPO AXIOMA | D50: 24000 | E50: 44154.61 | N50: SIM | O50: 44537 | P50: Proc: 1063276-74.2021.8.26.0576 | Q50: PREAXI CURSOS LTDA, inscrita no CNPJ nº 34.443.026/0001-26
A51: =VLOOKUP(C51,'BASE DE DADOS'!A:B,2,FALSE) -> ENSINA MAIS | B51: 29.067.072/0001-38 | C51: HFH MOURA PROGRAMAS EDUCACIONAIS EIRELI - ME | D51: 30671.75 | E51: 57181.51 | N51: SIM | O51: 44673 | P51: Proc: 1019941-68.2022.8.26.0576 | Q51: ENVIADO EM 16/03/2022.
A52: =VLOOKUP(C52,'BASE DE DADOS'!A:B,2,FALSE) -> PREPARA INATIVOS | B52: 070.883.265-23 | C52: IAGO DA CRUZ SANTOS | D52: 157712.63 | E52: 60496.88 | N52: SIM | O52: 44791 | P52: Proc: 1045338-32.2022.8.26.0576 | Q52: ENVIADO EM 06/06/2022.
A53: =VLOOKUP(C53,'BASE DE DADOS'!A:B,2,FALSE) -> MICROLINS INATIVOS | B53: 34.940.159/0001-08 | C53: INFRAMEGA TECNOLOGIA E EDUCACAO LTDA | D53: 87049.98 | E53: 40747.72 | N53: SIM | O53: 44956 | P53: Proc: 1004183-15.2023.8.26.0576 | Q53: ENVIADO EM 29/03/2022.
A54: =VLOOKUP(C54,'BASE DE DADOS'!A:B,2,FALSE) -> MICROLINS INATIVOS | B54: 39.940.159/0001-08 | C54: INFRAMEGA TECNOLOGIA E EDUCACAO LTDA | E54: 2.719,14 | N54: SIM | O54: 45610 | P54: Proc: 1001050-97.2024.8.26.0359
A55: =VLOOKUP(C55,'BASE DE DADOS'!A:B,2,FALSE) -> MICROLINS INATIVOS | B55: 07.274.215/0001-40 | C55: INSTITUTO DE FORM.PROF. ANDRE REBOU CAS | D55: 105682.28 | E55: 301596.47 | N55: SIM | O55: 44673 | P55: Proc: 1019942-53.2022.8.26.0576
A56: =VLOOKUP(C56,'BASE DE DADOS'!A:B,2,FALSE) -> MICROLINS INATIVOS | B56: 10.743.665/0001-49 | C56: INSTITUTO DE FORM.PROF.ANDRE REBOUC AS 2 | D56: 115103.09 | N56: SIM | O56: 44673 | Q56: FINALIZADO.
A57: =VLOOKUP(C57,'BASE DE DADOS'!A:B,2,FALSE) -> PREPARA INATIVOS | B57: 27.403.550/0001-08 | C57: J. DOS S.LOBO SERVICOS EDUCACIONAIS E ADMINIST ME | D57: 60550.92 | E57: 82277.36 | N57: SIM | O57: 44970 | P57: Proc: 1006970-17.2023.8.26.0576
A58: =VLOOKUP(C58,'BASE DE DADOS'!A:B,2,FALSE) -> PREPARA INATIVOS | B58: 27.403.550/0001-08 | C58: J. DOS S.LOBO SERVICOS EDUCACIONAIS E ADMINIST ME | D58: 70951.22 | E58: 70.951,22 | N58: SIM | O58: 45005 | P58: Proc: 1013857-17.2023.8.26.0576 | Q58: Monitória.
A59: MICROLINS | B59: 11.770.909/0001-45 | C59: J3D FORMACAO PROFISSIONAL LTDA ME | D59: 12753.78 | J59: SIM
A60: =VLOOKUP(C60,'BASE DE DADOS'!A:B,2,FALSE) -> MICROLINS INATIVOS | B60: 14.218.684/0001-07 | C60: JADE CURSOS PROFISSIONALIZANTES EIRELI - ME | D60: 80582.82 | E60: 95793.27 | N60: SIM | O60: 45036 | P60: Proc: 1019744-79.2023.8.26.0576 | Q60: ENVIADO EM 16/05/2022.
A61: =VLOOKUP(C61,'BASE DE DADOS'!A:B,2,FALSE) -> MICROLINS INATIVOS | B61: 13.611.490/0001-04 | C61: JBS SERVICOS EDUCACIONAL LTDA - EPP | D61: 92465.82 | E61: 122.919,93 | N61: SIM | O61: 44827 | P61: Proc: 1053251-65.2022.8.26.0576 | Q61: ENVIADO EM 08/11/2021 08:57, mandei novamente em 22/06/22.
A62: MICROLINS | B62: 19.802.940/0001-22 | C62: JERUSALEM CURSOS PROFISSIONALIZANTES LTDA | D62: 9456 | J62: SIM | Q62: BAIXAS REALIZADAS
A63: =VLOOKUP(C63,'BASE DE DADOS'!A:B,2,FALSE) -> PREPARA INATIVOS | B63: 335.815.868-35 | C63: JULIANA SILVA COIMBRA DOS SANTOS | D63: 60456.62 | J63: SIM | Q63: JÁ EXISTE PROCESSO DA MOVEEDU COBRANDO ESSES VALORES, SOLICITAMOS A DEVOLUÇÃO.
A64: =VLOOKUP(C64,'BASE DE DADOS'!A:B,2,FALSE) -> PREPARA INATIVOS | B64: 924.014.147-20 | C64: KARLA SOCORRO GUEDES DE ANDRADE | D64: 23633.72 | E64: 29851.89 | N64: SIM | O64: 44503 | P64: Proc: 0006973-86.2023.8.26.0576
A65: =VLOOKUP(C65,'BASE DE DADOS'!A:B,2,FALSE) -> PREPARA INATIVOS | B65: 18.006.784/0001-20 | C65: KR CURSOS E TREINAMENTOS LTDA | D65: 128835.89 | J65: SIM
A66: =VLOOKUP(C66,'BASE DE DADOS'!A:B,2,FALSE) -> PREPARA INATIVOS | B66: 18.006.784/0001-20 | C66: KR CURSOS E TREINAMENTOS LTDA | J66: SIM | Q66: Parecer reenviado EM 25/10/2023
A67: =VLOOKUP(C67,'BASE DE DADOS'!A:B,2,FALSE) -> SOS INATIVOS | B67: 12.920.704/0001-61 | C67: L3 EDUCACAO PROFISSIONAL LTDA - ME | D67: 3133.71 | E67: 2521.24 | N67: SIM | O67: 44600 | P67: Proc: 1004658-33.2022.8.26.0114
A68: =VLOOKUP(C68,'BASE DE DADOS'!A:B,2,FALSE) -> PREPARA INATIVOS | B68: 190.672.538-12 | C68: LEANDRO AUGUSTO COSTA | D68: 137519.43 | E68: 118694.73 | N68: SIM | O68: 44627 | P68: Proc: 1010769-05.2022.8.26.0576
A69: =VLOOKUP(C69,'BASE DE DADOS'!A:B,2,FALSE) -> ENSINA MAIS INATIVOS | B69: 964.219.243-87 | C69: LEONARDO IVAN DA PAZ ARAUJO | D69: 29591.78 | E69: 29.411,06 | N69: SIM | O69: 44573 | P69: Proc: 1000860-36.2022.8.26.0576 | Q69: ACORDO EFETUADO.
A70: PREPARA | B70: 388.029.965-04 | C70: LUIS MARTINS GOMES | D70: 66905.45 | J70: SIM | Q70: ENVIADO EM 28/04/2022.
A71: PEOPLE | B71: 17.974.263/0001-02 | C71: LUIZ FELIPE FERREIRA - ME | D71: 165010.29 | J71: SIM | Q71: Diante da ausência de documentação para embasar o ajuizamento.
A72: =VLOOKUP(C72,'BASE DE DADOS'!A:B,2,FALSE) -> PREPARA INATIVOS | B72: 807.356.220-00 | C72: LUIZ MATHEUS DORNELLES ACOSTA | D72: 28649.09 | J72: SIM | Q72: PARECER PARA BAIXA, POIS NÃO POSSUIMOS DOCUMENTOS PASSÍVEIS DE AJUIZAMENTO.
A73: =VLOOKUP(C73,'BASE DE DADOS'!A:B,2,FALSE) -> ENSINA MAIS INATIVOS | B73: 20.804.046/0001-70 | C73: M. E. B. ENSINO COMPLEMENTAR LTDA - ME | D73: 34168.03 | E73: 76596.17 | N73: SIM | O73: 44532 | P73: Proc: 1062075-47.2021.8.26.0576
A74: =VLOOKUP(C74,'BASE DE DADOS'!A:B,2,FALSE) -> PREPARA INATIVOS | B74: 11.250.516/0001-91 | C74: MAIS APROVACAO LTDA - ME | D74: 25443.76 | E74: 16573.93 | N74: SIM | O74: 44673 | P74: Proc: 1019939-98.2022.8.26.0576 | Q74: ENVIADO EM 16/03/2022.
A75: =VLOOKUP(C75,'BASE DE DADOS'!A:B,2,FALSE) -> MICROLINS INATIVOS | B75: 13.829.218/0001-03 | C75: MAIS INFORMATICA E TREINAMENTOS LTD A ME | D75: 179221.68 | E75: 322858.68 | N75: SIM | O75: 44694 | P75: Proc: 1019558-21.2022.8.26.0114 | Q75: CONTRATO POSSUÍ PROCESSOS JURÍDICOS VINCULADOS A OUTRAS NEGOCIAÇÕES / (BATIMENTO NO SISTEMA)
A76: =VLOOKUP(C76,'BASE DE DADOS'!A:B,2,FALSE) -> PREPARA INATIVOS | B76: 25.220.395/0001-69 | C76: MAURO MANFRINATTO JUNIOR - ME | D76: 58858.25 | E76: 32.233,98 | N76: SIM | O76: 44764 | P76: Proc: 1039406-63.2022.8.26.0576 | Q76: ENVIADO EM 01/04/2022. Execução
A77: =VLOOKUP(C77,'BASE DE DADOS'!A:B,2,FALSE) -> PREPARA INATIVOS | B77: 25.220.395/0001-69 | C77: MAURO MANFRINATTO JUNIOR - ME | D77: 60618.48 | E77: 60618.48 | N77: SIM | O77: 45155 | P77: Proc: 1041170-50.2023.8.26.0576 | Q77: Monitória
A78: =VLOOKUP(C78,'BASE DE DADOS'!A:B,2,FALSE) -> PREPARA INATIVOS | B78: 425.237.738-21 | C78: MAYARA BARBOSA POSCAI PIRES | D78: 10231.5 | E78: 205921.88 | N78: SIM | O78: 45603 | P78: Proc: 1050800-96.2024.8.26.0576 | Q78: ENVIADO EM 22/06/2022. Títulos não passíveis de ajuizamento (análise realizada pelo Dep. Judicial). Confissão localizada. Autorizado ajuizamento em 03/07/2024. 1050800-96.2024.8.26.0576
A79: =VLOOKUP(C79,'BASE DE DADOS'!A:B,2,FALSE) -> MICROLINS INATIVOS | B79: 10.944.091/0001-77 | C79: MGA LIVROS E FORMACAO PROFISSIONAL LTDA | D79: 141163.89 | E79: 95880.3 | N79: SIM | O79: 44855 | P79: Proc: 0025325-86.2024.8.26.0114 | Q79: REENVIADO EM 12/05/2022.
A80: =VLOOKUP(C80,'BASE DE DADOS'!A:B,2,FALSE) -> ENSINA MAIS INATIVOS | B80: 27.262.205/0001-00 | C80: MIRIAN E C VILLAGRAN MACHADO - ME | D80: 34781.18 | E80: 85027.27 | N80: SIM | O80: 44754 | P80: Proc: 1036773-79.2022.8.26.0576 | Q80: ENVIADO EM 22/03/2022.
A81: =VLOOKUP(C81,'BASE DE DADOS'!A:B,2,FALSE) -> PREPARA INATIVOS | B81: 17.988.662/0001-14 | C81: NARP CENTRO DE ENSINO PROFISSIONALIZANTE LTDA | D81: 265133.29 | E81: 280449.17 | N81: SIM | O81: 44631 | P81: Proc: 1011824-88.2022.8.26.0576
A82: =VLOOKUP(C82,'BASE DE DADOS'!A:B,2,FALSE) -> PREPARA INATIVOS | B82: 380.972.718-00 | C82: NATALIA RIBEIRO DO PRADO | D82: 80069.19 | E82: 89674.43 | N82: SIM | O82: 45084 | P82: Proc: 1028210-62.2023.8.26.0576 | Q82: ENVIADO EM 09/03/2022. Unidade FLEX - Aguarda baixa dos títulos da EM, 11/10.
A83: =VLOOKUP(C83,'BASE DE DADOS'!A:B,2,FALSE) -> MICROLINS | B83: 15.132.811/0001-13 | C83: NAYARA ALINE DE LIMA | D83: 83128.48 | E83: 114709.76 | N83: SIM | O83: 44725 | P83: Proc: 1031144-27.2022.8.26.0576 | Q83: BS.: NÃO ENCONTREI NESSE CNPJ - APENAS NO CPF DA NAYARA - NÃO ENCONTREI NEM A PASTA / ENVIADO EM 04/04/2022.
A84: =VLOOKUP(C84,'BASE DE DADOS'!A:B,2,FALSE) -> ENSINA MAIS INATIVOS | B84: 857.934.936-20 | C84: PATRICIA DIAS RIBEIRO E SILVA | D84: 11429.36 | E84: 10466.36 | N84: SIM | O84: 44848 | P84: Proc: 1057352-48.2022.8.26.0576 | Q84: ENVIADO EM 02/06/2022.
A85: =VLOOKUP(C85,'BASE DE DADOS'!A:B,2,FALSE) -> ENGLISH TALK INATIVOS | B85: 139.878.088-02 | C85: PAULO ROBERTO SIQUEIRA | D85: 30092.01 | E85: 45183.58 | N85: SIM | O85: 44844 | P85: Proc: 1056684-77.2022.8.26.0576 | Q85: ENVIADO EM 28/03/2022.
A86: =VLOOKUP(C86,'BASE DE DADOS'!A:B,2,FALSE) -> PREPARA INATIVOS | B86: 001.273.073-46 | C86: POLIMARQUES BISPO DOURADO | D86: 18713.02 | E86: 14118.71 | N86: SIM | O86: 44848 | P86: Proc: 1057356-85.2022.8.26.0576 | Q86: ENVIADO EM 12/09/2022.
A87: =VLOOKUP(C87,'BASE DE DADOS'!A:B,2,FALSE) -> PREPARA INATIVOS | B87: 11.324.881/0001-12 | C87: POLYANA R. DOS S. BOAVENTURA INFORMATICA | D87: 161995.07 | Q87: ENVIADO EM 20/07/2022. Aguarda aval para baixa parcial.Reiterado em 27/04/2023 e 15/06/2023 / PRESCRITO
A88: =VLOOKUP(C88,'BASE DE DADOS'!A:B,2,FALSE) -> PREPARA INATIVOS | B88: 14.193.192/0001-04 | C88: PREPARA CURSOS PROFISSIONALIZANTES - UNIDADE JUAZEIRO DO NOR | D88: 68745.54 | E88: 38872.82 | N88: SIM | O88: 44883 | P88: Proc: 1064281-97.2022.8.26.0576 | Q88: ENVIADO EM 29/06/2022.
A89: =VLOOKUP(C89,'BASE DE DADOS'!A:B,2,FALSE) -> PREPARA INATIVOS | B89: 13.018.523/0001-07 | C89: PREPARA CURSOS PROFISSIONALIZANTES-UNIDADE MARACANAU LTDA | D89: 16939.4 | E89: 18955.83 | N89: SIM | O89: 44956 | P89: Proc: 1004184-97.2023.8.26.0576 | Q89: ENVIADO EM 17/08/2022. - (Processo Suspenso - pois houve acordo, verificar andamento sobre o pagamento do acordo judicial)
A90: =VLOOKUP(C90,'BASE DE DADOS'!A:B,2,FALSE) -> ENSINA MAIS INATIVOS | B90: 12.544.850/0001-30 | C90: PRIME CURSOS DE FORMACAO PROFISSIONAL LTDA ME | D90: 60270.17 | E90: 99106.4 | N90: SIM | O90: 44509 | P90: Proc: 1057290-42.2021.8.26.0576 | Q90: Cumprimento de sentença - 0017936-56.2023.8.26.0576 - R$ 125.007,60 / 11/10/2023 às 14:16
A91: =VLOOKUP(C91,'BASE DE DADOS'!A:B,2,FALSE) -> PREPARA INATIVOS | B91: 28.763.624/0001-80 | C91: QUALIDADE EM EDUCACAO E CONSULTORIA EIRELI - ME | D91: 46408.1 | E91: 63516.94 | N91: SIM | O91: 44911 | P91: Proc: 1069860-26.2022.8.26.0576
A92: =VLOOKUP(C92,'BASE DE DADOS'!A:B,2,FALSE) -> ENSINA MAIS INATIVOS | B92: 312.906.168-17 | C92: RENATA DA SILVA ALBUQUERQUE | D92: 13933.16 | E92: 25142.77 | N92: SIM | O92: 44519 | P92: Proc: 1059245-11.2021.8.26.0576
A93: =VLOOKUP(C93,'BASE DE DADOS'!A:B,2,FALSE) -> PEOPLE INATIVOS | B93: 07.646.643/0001-56 | C93: RJO CURSOS E TREINAMENTOS LTDA - ME | D93: 241849.38 | E93: 45.508,01 | O93: 45772 | P93: Proc: 1017330-40.2025.8.26.0576 | Q93: ENVIADO EM 27/07/2022. Reenviado em 27/04 para Larissa. Victor não faz mais parte da MoveEdu. Unidade encerrou as atividades em 28/02/2023 / EXECUÇÃO REFERENTE AC 19833 - REN3862873166
A94: =VLOOKUP(C94,'BASE DE DADOS'!A:B,2,FALSE) -> PEOPLE INATIVOS | B94: 07.646.643/0001-56 | C94: RJO CURSOS E TREINAMENTOS LTDA - ME | E94: 148600.08 | O94: 45772 | P94: Proc: 1017344-24.2025.8.26.0576 | Q94: RENEGOCIAÇÃO MOVEEDU
A95: =VLOOKUP(C95,'BASE DE DADOS'!A:B,2,FALSE) -> PREPARA INATIVOS | B95: 108.277.807-96 | C95: RODRIGO MIRANDA LAMBLET FAJARDO | D95: 18320.62 | E95: 41.865,53 | N95: SIM | O95: 44827 | P95: Proc: 1051783-66.2022.8.26.0576 | Q95: AGUARDO GISLAINE SOBRE CHEQUES (OUTRA UNIDADE DO RODRIGO É A CTM)
A96: =VLOOKUP(C96,'BASE DE DADOS'!A:B,2,FALSE) -> PREPARA INATIVOS | B96: 11.407.560/0001-81 | C96: RT TREINAMENTO EM DESENVOLVIMENTO PROFISSIONAL LTD | D96: 95942.41 | E96: 172632.46 | N96: SIM | O96: 44524 | P96: Proc: 1060074-89.2021.8.26.0576 | Q96: Em grau de recurso
A97: MICROLINS | B97: 10.280.672/0001-51 | C97: S & C CURSOS E INOVAÇÕES LTDA | D97: 15573.71 | J97: SIM | Q97: ENVIADO EM 18/04/2022.
A98: =VLOOKUP(C98,'BASE DE DADOS'!A:B,2,FALSE) -> PREPARA INATIVOS | B98: 14.665.919/0001-09 | C98: SACAJ TREINAMENTO EM DESENVOLVIMENTO PROFISSIONAL LTDA | D98: 194731.96 | E98: 172053.91 | N98: SIM | O98: 44512 | P98: Proc: 1057868-05.2021.8.26.0576
A99: =VLOOKUP(C99,'BASE DE DADOS'!A:B,2,FALSE) -> PINGUS ENGLISH INATIVOS | B99: 28.199.203/0001-78 | C99: NAHIMAN GOBBO GUIDO SALLES SOUZA ENSINO DE IDIOMAS | D99: 61327.8 | Q99: ENVIADO EM 15/03/2022 PG0042. (NAHIMAN GOBBO GUIDO SALLES SOUZA ENSINO DE IDIOMAS) - PRESCRITO
A100: =VLOOKUP(C100,'BASE DE DADOS'!A:B,2,FALSE) -> PEOPLE INATIVOS | B100: 22.636.319/0001-40 | C100: SANCHES E LEITE IDIOMAS E INFORMATI CA L | D100: 35956.03 | E100: 86025.67 | N100: SIM | O100: 44645 | P100: Proc: 1012180-14.2022.8.26.0114
...

Sheet LEGENDA
A1: DESFAVORÁVEL
A2: AJUÍZADO / ANDAMENTO
A3: OVVA
A4: CONFERIR / EM ANDAMENTO
A5: PRESCRITOS
A6: AJUÍZADO COM TÍTULOS EM ABERTO
A7: VALOR BAIXO
A8: TAXA DE FRANQUIA (ANÁLISE)

Sheet BASE DE DADOS
A1: CLIENTE | B1: FILIAL
A2: 3 D ILHEUS INFORMATICA LTDA - ME | B2: MICROLINS
A3: 3C SISTEMAS LTDA | B3: PREPARA INATIVOS
A4: 3EMI EMPREENDIMENTOS LTDA ME | B4: PREPARA INATIVOS
A5: 5W2H EDUCACAO LTDA | B5: PREPARA
A6: 5W2H EDUCACAO LTDA | B6: PREPARA INATIVOS
A7: 5W2H EDUCACAO LTDA - ME | B7: PREPARA INATIVOS
A8: A & D EDUCACAO PROFISSIONAL E RECURSOS HUMANOS LTDA | B8: MICROLINS INATIVOS
A9: A & D TREINAMENTOS E CURSOS LTDA - ME | B9: PREPARA INATIVOS
A10: A & G CURSOS LTDA | B10: MICROLINS
A11: A & K CENTRO DE FORMACAO PROFISSIONAL LTDA | B11: MICROLINS
A12: A & S SERVICOS EDUCACIONAIS LTDA - ME | B12: PREPARA INATIVOS
... A2739: ZR TREINAMENTOS LTDA | B2739: MICROLINS

Sheet AJUIZADOS - AC CURSOS
A1: MARCA | B1: CNPJ/CPF | C1: NOME | D1: VALOR SISTEMA | E1: VALOR DA CAUSA | F1: AGUARDA PARECER MARCA | G1: AGUARDA PARECER JURÍDICO | H1: AGUARDA PARECER FINANCEIRO | I1: PARECER OK | J1: AGUARDA PROCURAÇÃO | K1: PRODUÇÃO | L1: PROTOCOLADA | M1: DATA DISTRIBUIÇÃO | N1: Nº DO PROCESSO | O1: OBSERVAÇÕES
A2: PEOPLE | B2: 06.693.085/0001-66 | C2: INTERFOCUS FRIBURGO CAP.PROF. E INF. LTDA | D2: 9329.05 | E2: 12527.04 | L2: SIM | M2: 45537 | N2: 1040108-38.2024.8.26.0576 | O2: PP0202 - AC31126. Enviado em 07/06/2024
A3: PEOPLE | B3: 06.671.085/0001-66 | C3: INTERFOCUS FRIBURGO CAP.PROF. E INF. LTDA | D3: 71304.54 | E3: 85692.93 | L3: SIM | M3: 45537 | N3: 1040155-12.2024.8.26.0576 | O3: PP0202 - AC31130. Enviado em 07/06/2024
A4: PEOPLE | B4: 31.206.339/0001-72 | C4: EDUCATION IN CENTER - CONSULTORIA LTDA | D4: 47544.29 | E4: 105084.64 | L4: SIM | M4: 45610 | N4: 1051748-38.2024.8.26.0576 | O4: PP0217 - AC21326. Enviado em 07/06/2024.
A5: SOS | B5: 20.116.895/0001-31 | C5: CRISANE QUALIFICAÇÃO E IDIOMAS EIRELLI | D5: 98423.34 | E5: 129841.68 | L5: SIM | M5: 45518 | N5: 1036892-69.2024.8.26.0576 | O5: SO0089 - REN3862872957 (AC28229). Enviado em 11/06/2024
A6: SOS | B6: 20.116.895/0001-35 | C6: CRISANE QUALIFICAÇÃO E IDIOMAS EIRELLI | D6: 8949.4 | E6: 14962.57 | L6: SIM | M6: 45516 | N6: 1036531-52.2024.8.26.0576 | O6: SO0089 - REN3862872958 (AC28236). Enviado em 11/06/2024. 1036531-52.2024.8.26.0576
A7: SOS | B7: 09.584.729/0001-27 | C7: MASOFT SISTEMAS LTDA - SKL EDUCAÇÃO E INFORMÁTICA LTDA | D7: 11218.4 | E7: 129841.68 | F7: SIM | O7: SO0084 - REN3862873191 (AC29865). Enviado em 21/06/2024. Devor não é a PJ
A8: MICROLINS | B8: 697.775.432-04 | C8: CLAUDIO DAISHONIN SAUNDERS FLORENCIA | D8: 30213.35 | F8: SIM | O8: MC1340. REN3862872951 (AC32089). Enviado em 09/07/2024
A9: MICROLINS | B9: 37.683.797/0001-89 | C9: ESCOLA PROFISSIONALIZANTE E RECURSOS HUMANOS EIRELI | D9: 36607.37 | F9: SIM | O9: MC1335. REN50043. Enviado em 09/07/2024
A10: MICROLINS | B10: 20.140.534/0001-20 | C10: J.C. FORMACAO PROFISSIONAL LTDA | D10: 26399.83 | E10: 35527.57 | L10: SIM | M10: 45567 | N10: 1044905-57.2024.8.26.0576 | O10: MC0365. REN3862873043 (AC24584). Enviado em 09/07/2024
A11: MICROLINS | B11: 20.140.534/0001-20 | C11: J.C. FORMACAO PROFISSIONAL LTDA | D11: 1645.59 | E11: 2210.92 | L11: SIM | M11: 45554 | N11: 1042876-34.2024.8.26.0576 | O11: MC0365. REN3862873045 (AC30947). Enviado em 09/07/2024
A12: MICROLINS | B12: 20.140.534/0001-20 | C12: J.C. FORMACAO PROFISSIONAL LTDA | D12: 1394.07 | E12: 1612.89 | L12: SIM | M12: 45559 | N12: 1043558-86.2024.8.26.0576 | O12: MC0365. REN3862873044 (AC29669). Enviado em 09/07/2024.
A13: MICROLINS | B13: 05.291.973/0001-40 | C13: HMK CURSOS DE INFORMATICA PROFISSIONALIZANTES S/S LTDA | D13: 114412.9 | E13: 140350.64 | L13: SIM | M13: 45537 | N13: 1040055-57.2024.8.26.0576 | O13: MC0198. REN3862873033 (29996). Enviado em 09/07/2024
A14: MICROLINS | B14: 05.291.793/0001-40 | C14: HMK CURSOS DE INFORMATICA PROFISSIONALIZANTES S/S LTDA | D14: 1670.68 | E14: 2026.6 | L14: SIM | M14: 45520 | N14: 1037421-88.2024.8.26.0576 | O14: MC0198.REN3862873034 (AC1003). Enviado em 09/07/2024
A15: MICROLINS | B15: 088.163.614-25 | C15: KASSIA TASSYANA DOS SANTOS VASCONCELOS MAGALHAES | D15: 171813.16 | E15: 126849.22 | L15: SIM | M15: 45567 | N15: 1044939-32.2024.8.26.0576 | O15: MC0198.REN3862873034 (AC1003). Enviado em 09/07/2024
A16: MICROLINS | B16: 11.362.578/0001-04 | C16: PAZ E CHAVES LTDA | D16: 118672.21 | F16: DESFAVORÁVEL | O16: MC0289. REN3862873141 (AC34442). Enviado em 19/07/2024. Nancy mencionou que a unidade está ativa
A17: MICROLINS | B17: 05.229.602/0001-39 | C17: C & C TREINAMENTOS LTDA | D17: 66734.12 | E17: 94018.12 | L17: SIM | M17: 45631 | O17: MC0147. REN3862872916 (AC30974). Enviado em 29/07/2024. Proc. 1054777-96.2024.8.26.0576
A18: MICROLINS | B18: 05.229.602/0001-39 | C18: C & C TREINAMENTOS LTDA | D18: 1457.81 | L18: SIM | M18: 45631 | O18: MC0147. REN3862872917 (AC32951). Enviado em 29/07/2024 Proc. 1054777-96.2024.8.26.0576
A19: MICROLINS | B19: 05.229.602/0001-39 | C19: C & C TREINAMENTOS LTDA | D19: 11282.44 | L19: SIM | M19: 45631 | O19: MC0147. REN3862872918 (AC 32954). Enviado em 29/07/2024 Proc. 1054777-96.2024.8.26.0576
A20: SOS | B20: 21.556.648/0001-19 | C20: TEMPO SOLUCOES EM EDUCACAO LTDA ME | D20: 2106.36 | E20: 3491.16 | L20: SIM | M20: 45576 | N20: 1046418-60.2024.8.26.0576 | O20: SO0094. REN3862873201 (AC 28894). Enviado em 31/07/2024
A21: SOS | B21: 21.556.648/0001-19 | C21: TEMPO SOLUCOES EM EDUCACAO LTDA ME | D21: 58616.52 | E21: 75152.87 | L21: SIM | M21: 45614 | N21: 1052051-52.2024.8.26.0576 | O21: SO0094. REN3862873202 (AC 28927). Enviado em 31/07/2024
A22: SOS | B22: 17.522.270/0001-65 | C22: MILENIO CURSOS E TREINAMENTOS EIRELI | D22: 12985.78 | E22: 16207.47 | L22: SIM | M22: 45573 | N22: 1045855-66.2024.8.26.0576 | O22: SO0271. REN3862873108 (AC 30995). Enviado em 31/07/2024
A23: MICROLINS | B23: 18.226.478/0001-08 | C23: ECGG CURSOS LTDA - ME | D23: 41639.47 | K23: SIM | O23: MC0361. REN3862872986 (AC 30815). Enviado em 12/08/2024. Devedor não é a PJ
A24: MICROLINS | B24: 26.801.548/0001-50 | C24: ABJ CURSOS PROFISSIONALIZANTES LTDA ME | D24: 6364.86 | F24: SIM | O24: MC0530. REN3862872884 (AC24179). Enviado em 27/08/2024.
A25: PEOPLE | B25: 41.512.896/0001-75 | C25: B&J CURSOS TECNICOS EM INFORMATICA LTDA | D25: 1241.11 | F25: SIM | O25: PP0267. REN3862872911 (AC31033). Enviado e-mail em 12/08/2024. Estão verificando distrato/quitação
A26: MICROLINS | B26: 05.380.319/0001-03 | C26: H B CENTRO DE FORMAÇÃO PROFISSIONAL LTDA | D26: 9066.22 | F26: SIM | O26: MC0300. REN3862873029 (AC23142). Enviado em 29/08/2024
A27: MICROLINS | B27: 12.213.218/0001-03 | C27: JF CURSOS E INFORMATICA LTDA ME | D27: 113623.86 | F27: SIM | O27: MC0237. REN3862873059 (AC 27350). Enviado em 17/09/2024
A28: PEOPLE | B28: 08.893.793/0003-99 | C28: JGM CENTRO DE IDIOMAS LTDA-ME | D28: 208100.69 | F28: SIM | O28: PP0060. REN3862873060 (AC30988). Enviado em 18/09/2024
A29: MICROLINS | B29: 08.335.434/0001-54 | C29: TAIS CRISTINA FRANCISCO ME | D29: 80728.02 | F29: SIM | O29: MC0207. REN3862873197 (AC34480). Enviado em 12/12/2024
A30: MICROLINS | B30: 17.027.496/0001-90 | C30: EDUPRO GUADALUPE LTDA | D30: 46336.12 | F30: SIM | O30: MC0315. REN3862872994 (AC 34337). Enviado em 12/12/2024
A31: MICROLINS | B31: 24.604.424/0001-23 | C31: SAMPAIO PROJETOS E CONSULTORIA | D31: 51863.28 | F31: SIM | O31: MC0260. REN3862873180 (AC 24258). Enviado em 13/12/2024
A32: MICROLINS | B32: 36.562.622/0001-50 | C32: ART CRIS TREINAMENTOS E DESENVOLVIMENTO LTDA | D32: 10316.29 | F32: SIM | O32: MC1626. REN50143. Enviado em 18/12/2024

Sheet PAINEL Novo
